tess/__init__.py
tess/resources/__init__.py
tess/resources/config/__init__.py
tess/resources/config/compilers.json
tess/resources/config/runners.json
tess/resources/scripts/__init__.py
tess/resources/scripts/bash-completion.sh
tess/resources/scripts/zsh-completion.sh
tess/resources/templates/__init__.py
tess/resources/templates/cases/__init__.py
tess/resources/templates/cases/lower-bound.txt
tess/resources/templates/cases/upper-bound.txt
tess/resources/templates/cpp/__init__.py
tess/resources/templates/cpp/model.cpp
tess/resources/templates/cpp/solution.cpp
tess/resources/templates/generators/__init__.py
tess/resources/templates/generators/empty.py
tess/resources/templates/generators/sum_template.py
tess/resources/templates/java/Model.java
tess/resources/templates/java/Solution.java
tess/resources/templates/java/__init__.py
tess/resources/templates/py/__init__.py
tess/resources/templates/py/model.py
tess/resources/templates/py/solution.py
tess/src/__init__.py
tess/src/cli.py
tess/src/compiler.py
tess/src/directories.py
tess/src/initializer.py
tess/src/logger.py
tess/src/navigator.py
tess/src/resources.py
tess/src/runner.py
tess/src/scripts.py
tess/src/stresser.py
tess_cli-0.1.1.dist-info/LICENSE
tess_cli-0.1.1.dist-info/METADATA
tess_cli-0.1.1.dist-info/WHEEL
tess_cli-0.1.1.dist-info/entry_points.txt
tess_cli-0.1.1.dist-info/top_level.txt
tess_cli-0.1.1.dist-info/RECORD
