Metadata-Version: 2.1
Name: tess-cli
Version: 0.1.1
Summary: CLI tool for testing algorithms.
Home-page: https://github.com/andresscode/tess
Author: Andres Martinez
Author-email: andressbox90@gmail.com
License: UNKNOWN
Platform: UNKNOWN
Classifier: Programming Language :: Python :: 3
Classifier: License :: OSI Approved :: MIT License
Classifier: Operating System :: POSIX :: Linux
Classifier: Operating System :: MacOS
Requires-Python: >=3.7
Requires-Dist: Click
